cinema4d_mcp/__init__.py
cinema4d_mcp/config.py
cinema4d_mcp/server.py
cinema4d_mcp/utils.py
iflow_mcp_cinema4d_mcp-0.1.2.dist-info/licenses/LICENSE
iflow_mcp_cinema4d_mcp-0.1.2.dist-info/METADATA
iflow_mcp_cinema4d_mcp-0.1.2.dist-info/WHEEL
iflow_mcp_cinema4d_mcp-0.1.2.dist-info/entry_points.txt
iflow_mcp_cinema4d_mcp-0.1.2.dist-info/top_level.txt
iflow_mcp_cinema4d_mcp-0.1.2.dist-info/RECORD
